cognia/__init__.py
cognia/alert.py
cognia/corr.py
cognia/interpret.py
cognia/missing.py
cognia/outliers.py
cognia/profiling.py
cognia/quick_eda.py
cognia/report.py
cognia/stats.py
cognia-0.1.0.dist-info/licenses/LICENSE
cognia-0.1.0.dist-info/METADATA
cognia-0.1.0.dist-info/WHEEL
cognia-0.1.0.dist-info/top_level.txt
cognia-0.1.0.dist-info/RECORD
