Metadata-Version: 2.4
Name: cognia
Version: 0.1.0
Summary: Cognia – Automated Exploratory Data Analysis (EDA) with HTML reports
Author-email: Kashish Pundir <your_email@gmail.com>
License: MIT License
Project-URL: Homepage, https://github.com/KashishPundir/Cognia
Project-URL: Repository, https://github.com/KashishPundir/Cognia
Project-URL: Issues, https://github.com/KashishPundir/Cognia/issues
Classifier: Programming Language :: Python :: 3
Classifier: License :: OSI Approved :: MIT License
Classifier: Operating System :: OS Independent
Requires-Python: >=3.9
License-File: LICENSE
Requires-Dist: pandas
Requires-Dist: numpy
Requires-Dist: matplotlib
Dynamic: license-file
